odoo/addons/purchase_order_payment_term_report/README.rst
odoo/addons/purchase_order_payment_term_report/__init__.py
odoo/addons/purchase_order_payment_term_report/__manifest__.py
odoo/addons/purchase_order_payment_term_report/i18n/it.po
odoo/addons/purchase_order_payment_term_report/i18n/purchase_order_payment_term_report.pot
odoo/addons/purchase_order_payment_term_report/models/__init__.py
odoo/addons/purchase_order_payment_term_report/models/purchase_order.py
odoo/addons/purchase_order_payment_term_report/readme/CONTRIBUTORS.rst
odoo/addons/purchase_order_payment_term_report/readme/DESCRIPTION.rst
odoo/addons/purchase_order_payment_term_report/reports/report_purchase_order.xml
odoo/addons/purchase_order_payment_term_report/static/description/icon.png
odoo/addons/purchase_order_payment_term_report/static/description/index.html
odoo/addons/purchase_order_payment_term_report/views/purchase_order.xml
odoo14_addon_purchase_order_payment_term_report-14.0.1.0.1.dist-info/METADATA
odoo14_addon_purchase_order_payment_term_report-14.0.1.0.1.dist-info/WHEEL
odoo14_addon_purchase_order_payment_term_report-14.0.1.0.1.dist-info/top_level.txt
odoo14_addon_purchase_order_payment_term_report-14.0.1.0.1.dist-info/RECORD
